servermind_cli/__init__.py
servermind_cli/config.py
servermind_cli/executor.py
servermind_cli/filter.py
servermind_cli/interpreter.py
servermind_cli/logger.py
servermind_cli/main.py
servermind_cli/translator.py
servermind_cli/utils.py
servermind_cli-0.2.2.dist-info/METADATA
servermind_cli-0.2.2.dist-info/WHEEL
servermind_cli-0.2.2.dist-info/entry_points.txt
servermind_cli-0.2.2.dist-info/top_level.txt
servermind_cli-0.2.2.dist-info/RECORD
