Metadata-Version: 2.1
Name: servermind_cli
Version: 0.2.2
Summary: ServerMind CLI - AI-powered command line interface
Home-page: https://github.com/yourusername/servermind-cli
Author: ServerMind
Author-email: support@servermind.ai
Classifier: Programming Language :: Python :: 3
Classifier: License :: OSI Approved :: MIT License
Classifier: Operating System :: OS Independent
Requires-Python: >=3.9
Requires-Dist: openai
Requires-Dist: python-dotenv
Requires-Dist: rich
Requires-Dist: click
